nopea/__init__.py
nopea/dbobject.py
nopea/exceptions.py
nopea/fields.py
nopea/managers.py
nopea/migrations.py
nopea/queryset.py
nopea/adaptors/__init__.py
nopea/adaptors/mysql.py
nopea/adaptors/postgres.py
nopea/adaptors/sqlite.py
nopea-0.0.29.dist-info/METADATA
nopea-0.0.29.dist-info/WHEEL
nopea-0.0.29.dist-info/top_level.txt
nopea-0.0.29.dist-info/RECORD
