Metadata-Version: 2.1
Name: nopea
Version: 0.0.29
Summary: Provides an ORM for MySQL, PostgreSQL and SQLite.
Home-page: UNKNOWN
Author: Christian Kokoska
Author-email: info@softcreate.de
License: GPLv3
Platform: UNKNOWN
Requires-Dist: colorama (==0.3.9)
Requires-Dist: ipython
